plantuml_local_client/__init__.py
plantuml_local_client/__main__.py
plantuml_local_client/plantuml.1.2022.6.jar
plantuml_local_client-1.2022.6.dist-info/METADATA
plantuml_local_client-1.2022.6.dist-info/WHEEL
plantuml_local_client-1.2022.6.dist-info/entry_points.txt
plantuml_local_client-1.2022.6.dist-info/top_level.txt
plantuml_local_client-1.2022.6.dist-info/RECORD
