Metadata-Version: 2.1
Name: plantuml-local-client
Version: 1.2022.6
Summary: PlantUML : a free UML diagram generator - A Python wrapper script around PlantUML. Provides a "plantuml" command
Home-page: https://plantuml.com/
Author: Arnaud Roques
Platform: any
Classifier: Programming Language :: Java
Classifier: Programming Language :: Python :: 3.5
Classifier: License :: OSI Approved :: GNU General Public License v3 or later (GPLv3+)
Classifier: Topic :: Software Development :: Documentation
Classifier: Topic :: Scientific/Engineering :: Visualization
Requires-Python: >=3.5
